modraw/__init__.py
modraw/static/draw.css
modraw/static/draw.js
modraw-0.1.14.dist-info/licenses/LICENSE
tests/__init__.py
tests/test_basics.py
modraw-0.1.14.dist-info/METADATA
modraw-0.1.14.dist-info/WHEEL
modraw-0.1.14.dist-info/top_level.txt
modraw-0.1.14.dist-info/RECORD
